README.md
setup.py
vna/__init__.py
vna/vna.py
vna.egg-info/PKG-INFO
vna.egg-info/SOURCES.txt
vna.egg-info/dependency_links.txt
vna.egg-info/top_level.txt