Metadata-Version: 1.2
Name: vna
Version: 0.0.5
Summary: Instrument control library for the PicoVNA 106 and PicoVNA 108. Please note that additional libraries are required, not installed by this package. See the Python Programming Manual for details.
Home-page: http://picotech.com
Author: AAI Robotics Ltd
Author-email: help@aairobotics.com
License: MIT
Platform: UNKNOWN
Classifier: Development Status :: 5 - Production/Stable
Classifier: Programming Language :: Python :: 3
Classifier: License :: OSI Approved :: MIT License
Classifier: Operating System :: Microsoft :: Windows
Classifier: Operating System :: Unix
Classifier: Operating System :: MacOS
Requires-Python: >=3.8
